LICENSE
MANIFEST.in
README.md
pyproject.toml
setup.py
scanpro/__init__.py
scanpro/_version.py
scanpro/ebayes.py
scanpro/fitFDist.py
scanpro/gaussq2.py
scanpro/get_transformed_props.py
scanpro/linear_model.py
scanpro/logging.py
scanpro/result.py
scanpro/scanpro.py
scanpro/sim_reps.py
scanpro/utils.py
scanpro.egg-info/PKG-INFO
scanpro.egg-info/SOURCES.txt
scanpro.egg-info/dependency_links.txt
scanpro.egg-info/requires.txt
scanpro.egg-info/top_level.txt