Metadata-Version: 2.1
Name: scanpro
Version: 0.4.0
Summary: Single-Cell Analysis of Proportions
Home-page: https://github.com/loosolab/scanpro
Author: Loosolab
Author-email: yousef.alayoubi@mpi-bn.mpg.de
License: MIT
License-File: LICENSE
